power_ai/weather_mcp/main.py
power_ai_weather_mcp-0.5.0.dist-info/METADATA
power_ai_weather_mcp-0.5.0.dist-info/WHEEL
power_ai_weather_mcp-0.5.0.dist-info/entry_points.txt
power_ai_weather_mcp-0.5.0.dist-info/top_level.txt
power_ai_weather_mcp-0.5.0.dist-info/RECORD
