Metadata-Version: 2.4
Name: power-ai-weather-mcp
Version: 0.5.0
Summary: 用以访问基于位置的天气数据，包括实况天气、逐小时预报、空气质量AQI，灾害预警、分钟级降水、生活建议、台风等天气数据服务
License-Expression: MIT
Requires-Python: >=3.10
Requires-Dist: mcp>=1.8.1
Requires-Dist: python-dotenv>=0.19.0
Requires-Dist: requests>=2.26.0
Requires-Dist: urllib3>=1.26.0
Requires-Dist: pydantic>=1.8.2
Requires-Dist: uvicorn>=0.15.0
Requires-Dist: uuid>=1.30
Requires-Dist: power-ai-common>=0.0.1
